build/fir.sv
`timescale 1ns / 1ps
// Generated by CIRCT firtool-1.62.1-1-gdf5ed6ea5
module FIRCore(
  input         clock,
                reset,
  input  [31:0] io_in_value,
  output [31:0] io_out_value
);

  reg  [31:0] regs_0_value;
  reg  [31:0] regs_1_value;
  reg  [31:0] regs_2_value;
  reg  [31:0] regs_3_value;
  reg  [31:0] regs_4_value;
  reg  [31:0] regs_5_value;
  reg  [31:0] regs_6_value;
  reg  [31:0] regs_7_value;
  reg  [31:0] regs_8_value;
  reg  [31:0] regs_9_value;
  reg  [31:0] regs_10_value;
  reg  [31:0] regs_11_value;
  reg  [31:0] regs_12_value;
  reg  [31:0] regs_13_value;
  reg  [31:0] regs_14_value;
  reg  [31:0] regs_15_value;
  wire [51:0] _io_out_fl_value_T = {{20{regs_0_value[31]}}, regs_0_value} * 52'h280E;
  wire [51:0] _io_out_fl_value_T_2 = {{20{regs_1_value[31]}}, regs_1_value} * 52'h3BF8;
  wire [51:0] _io_out_fl_value_T_4 = {{20{regs_2_value[31]}}, regs_2_value} * 52'h7445;
  wire [51:0] _io_out_fl_value_T_6 = {{20{regs_3_value[31]}}, regs_3_value} * 52'hC737;
  wire [51:0] _io_out_fl_value_T_8 = {{20{regs_4_value[31]}}, regs_4_value} * 52'h12679;
  wire [51:0] _io_out_fl_value_T_10 = {{20{regs_5_value[31]}}, regs_5_value} * 52'h18190;
  wire [51:0] _io_out_fl_value_T_12 = {{20{regs_6_value[31]}}, regs_6_value} * 52'h1C8BE;
  wire [51:0] _io_out_fl_value_T_14 = {{20{regs_7_value[31]}}, regs_7_value} * 52'h1EFB3;
  wire [51:0] _io_out_fl_value_T_16 = {{20{regs_8_value[31]}}, regs_8_value} * 52'h1EFB3;
  wire [51:0] _io_out_fl_value_T_18 = {{20{regs_9_value[31]}}, regs_9_value} * 52'h1C8BE;
  wire [51:0] _io_out_fl_value_T_20 =
    {{20{regs_10_value[31]}}, regs_10_value} * 52'h18190;
  wire [51:0] _io_out_fl_value_T_22 =
    {{20{regs_11_value[31]}}, regs_11_value} * 52'h12679;
  wire [51:0] _io_out_fl_value_T_24 = {{20{regs_12_value[31]}}, regs_12_value} * 52'hC737;
  wire [51:0] _io_out_fl_value_T_26 = {{20{regs_13_value[31]}}, regs_13_value} * 52'h7445;
  wire [51:0] _io_out_fl_value_T_28 = {{20{regs_14_value[31]}}, regs_14_value} * 52'h3BF8;
  wire [51:0] _io_out_fl_value_T_30 = {{20{regs_15_value[31]}}, regs_15_value} * 52'h280E;
  always @(posedge clock) begin
    if (reset) begin
      regs_0_value <= 32'h0;
      regs_1_value <= 32'h0;
      regs_2_value <= 32'h0;
      regs_3_value <= 32'h0;
      regs_4_value <= 32'h0;
      regs_5_value <= 32'h0;
      regs_6_value <= 32'h0;
      regs_7_value <= 32'h0;
      regs_8_value <= 32'h0;
      regs_9_value <= 32'h0;
      regs_10_value <= 32'h0;
      regs_11_value <= 32'h0;
      regs_12_value <= 32'h0;
      regs_13_value <= 32'h0;
      regs_14_value <= 32'h0;
      regs_15_value <= 32'h0;
    end
    else begin
      regs_0_value <= io_in_value;
      regs_1_value <= regs_0_value;
      regs_2_value <= regs_1_value;
      regs_3_value <= regs_2_value;
      regs_4_value <= regs_3_value;
      regs_5_value <= regs_4_value;
      regs_6_value <= regs_5_value;
      regs_7_value <= regs_6_value;
      regs_8_value <= regs_7_value;
      regs_9_value <= regs_8_value;
      regs_10_value <= regs_9_value;
      regs_11_value <= regs_10_value;
      regs_12_value <= regs_11_value;
      regs_13_value <= regs_12_value;
      regs_14_value <= regs_13_value;
      regs_15_value <= regs_14_value;
    end
  end // always @(posedge)
  assign io_out_value =
    _io_out_fl_value_T[51:20] + _io_out_fl_value_T_2[51:20] + _io_out_fl_value_T_4[51:20]
    + _io_out_fl_value_T_6[51:20] + _io_out_fl_value_T_8[51:20]
    + _io_out_fl_value_T_10[51:20] + _io_out_fl_value_T_12[51:20]
    + _io_out_fl_value_T_14[51:20] + _io_out_fl_value_T_16[51:20]
    + _io_out_fl_value_T_18[51:20] + _io_out_fl_value_T_20[51:20]
    + _io_out_fl_value_T_22[51:20] + _io_out_fl_value_T_24[51:20]
    + _io_out_fl_value_T_26[51:20] + _io_out_fl_value_T_28[51:20]
    + _io_out_fl_value_T_30[51:20];
endmodule

build/fir_tb.sv
`timescale 1ns / 1ps

module FIR_tb;
  reg clock;
  reg reset;
  reg [31:0] io_in_value;
  wire [31:0] io_out_value;

  // Instantiate the SineWave module
  FIRCore uut (
      .clock(clock),
      .reset(reset),
      .io_in_value(io_in_value),
      .io_out_value(io_out_value)
  );

  // Clock generation
  always #5 clock = ~clock;  // 10ns period -> 100MHz clock

  initial begin
    $dumpfile("fir.vcd");
    $dumpvars(0, FIR_tb);
    // Initialize signals
    clock = 0;
    reset = 1;

    // Apply reset
    #20;
    reset = 0;
    // Sinewave input
    for (int i = 0; i < 20000; i++) begin
      io_in_value = $rtoi($sin(2.0 * $acos(-1) * i / 10) * $pow(2, 20)) +
          $rtoi($sin(2.0 * $acos(-1) * i / 1000) * $pow(2, 20));
      #10;
    end

    // End simulation
    $finish;
  end


endmodule

build/obj_dir/limiter.vcd
$version Generated by VerilatedVcd $end
$timescale 1ps $end
 $scope module $rootio $end
 $upscope $end
 $scope module FIR_tb $end
  $var wire 1 4 clock $end
  $var wire 1 5 reset $end
  $var wire 32 6 io_in_value [31:0] $end
  $var wire 32 # io_out_value [31:0] $end
  $scope module unnamedblk1 $end
   $var wire 32 7 i [31:0] $end
  $upscope $end
  $scope module uut $end
   $var wire 1 4 clock $end
   $var wire 1 5 reset $end
   $var wire 32 6 io_in_value [31:0] $end
   $var wire 32 # io_out_value [31:0] $end
   $var wire 32 $ regs_0_value [31:0] $end
   $var wire 32 % regs_1_value [31:0] $end
   $var wire 32 & regs_2_value [31:0] $end
   $var wire 32 ' regs_3_value [31:0] $end
   $var wire 32 ( regs_4_value [31:0] $end
   $var wire 32 ) regs_5_value [31:0] $end
   $var wire 32 * regs_6_value [31:0] $end
   $var wire 32 + regs_7_value [31:0] $end
   $var wire 32 , regs_8_value [31:0] $end
   $var wire 32 - regs_9_value [31:0] $end
   $var wire 32 . regs_10_value [31:0] $end
   $var wire 32 / regs_11_value [31:0] $end
   $var wire 32 0 regs_12_value [31:0] $end
   $var wire 32 1 regs_13_value [31:0] $end
   $var wire 32 2 regs_14_value [31:0] $end
   $var wire 32 3 regs_15_value [31:0] $end
  $upscope $end
 $upscope $end
$enddefinitions $end


#0
b00000000000000000000000000000000 #
b00000000000000000000000000000000 $
b00000000000000000000000000000000 %
b00000000000000000000000000000000 &
b00000000000000000000000000000000 '
b00000000000000000000000000000000 (
b00000000000000000000000000000000 )
b00000000000000000000000000000000 *
b00000000000000000000000000000000 +
b00000000000000000000000000000000 ,
b00000000000000000000000000000000 -
b00000000000000000000000000000000 .
b00000000000000000000000000000000 /
b00000000000000000000000000000000 0
b00000000000000000000000000000000 1
b00000000000000000000000000000000 2
b00000000000000000000000000000000 3
04
15
b00000000000000000000000000000000 6
b00000000000000000000000000000000 7
#5000
14
#10000
04
#15000
14
#20000
04
05
#25000
14
#30000
04
b00000000000000010000001111000010 6
b00000000000000000000000000000001 7
#35000
b00000000000000000000001010001010 #
b00000000000000010000001111000010 $
14
#40000
04
b00000000000000100000011010000010 6
b00000000000000000000000000000010 7
#45000
b00000000000000000000100011011111 #
b00000000000000100000011010000010 $
b00000000000000010000001111000010 %
14
#50000
04
b00000000000000110000011100111011 6
b00000000000000000000000000000011 7
#55000
b00000000000000000001011010001010 #
b00000000000000110000011100111011 $
b00000000000000100000011010000010 %
b00000000000000010000001111000010 &
14
#60000
04
b00000000000001000000010011101101 6
b00000000000000000000000000000100 7
#65000
b00000000000000000011000011000001 #
b00000000000001000000010011101101 $
b00000000000000110000011100111011 %
b00000000000000100000011010000010 &
b00000000000000010000001111000010 '
14
#70000
04
b00000000000001001111111010011001 6
b00000000000000000000000000000101 7
#75000
b00000000000000000101110101110100 #
b00000000000001001111111010011001 $
b00000000000001000000010011101101 %
b00000000000000110000011100111011 &
b00000000000000100000011010000010 '
b00000000000000010000001111000010 (
14
#80000
04
b00000000000001011111001101000111 6
b00000000000000000000000000000110 7
#85000
b00000000000000001010001000111111 #
b00000000000001011111001101000111 $
b00000000000001001111111010011001 %
b00000000000001000000010011101101 &
b00000000000000110000011100111011 '
b00000000000000100000011010000010 (
b00000000000000010000001111000010 )
14
#90000
04
b00000000000001101110001000000000 6
b00000000000000000000000000000111 7
#95000
b00000000000000010000001101011110 #
b00000000000001101110001000000000 $
b00000000000001011111001101000111 %
b00000000000001001111111010011001 &
b00000000000001000000010011101101 '
b00000000000000110000011100111011 (
b00000000000000100000011010000010 )
b00000000000000010000001111000010 *
14
#100000
04
b00000000000001111100100111011001 6
b00000000000000000000000000001000 7
#105000
b00000000000000011000001011101000 #
b00000000000001111100100111011001 $
b00000000000001101110001000000000 %
b00000000000001011111001101000111 &
b00000000000001001111111010011001 '
b00000000000001000000010011101101 (
b00000000000000110000011100111011 )
b00000000000000100000011010000010 *
b00000000000000010000001111000010 +
14
#110000
04
b00000000000010001010100111101000 6
b00000000000000000000000000001001 7
#115000
b00000000000000100010000001100001 #
b00000000000010001010100111101000 $
b00000000000001111100100111011001 %
b00000000000001101110001000000000 &
b00000000000001011111001101000111 '
b00000000000001001111111010011001 (
b00000000000001000000010011101101 )
b00000000000000110000011100111011 *
b00000000000000100000011010000010 +
b00000000000000010000001111000010 ,
14
#120000
04
b00000000000010011000000101001101 6
b00000000000000000000000000001010 7
#125000
b00000000000000101101100010101110 #
b00000000000010011000000101001101 $
b00000000000010001010100111101000 %
b00000000000001111100100111011001 &
b00000000000001101110001000000000 '
b00000000000001011111001101000111 (
b00000000000001001111111010011001 )
b00000000000001000000010011101101 *
b00000000000000110000011100111011 +
b00000000000000100000011010000010 ,
b00000000000000010000001111000010 -
14
#130000
04
b00000000000010100100111100110010 6
b00000000000000000000000000001011 7
#135000
b00000000000000111010011010011001 #
b00000000000010100100111100110010 $
b00000000000010011000000101001101 %
b00000000000010001010100111101000 &
b00000000000001111100100111011001 '
b00000000000001101110001000000000 (
b00000000000001011111001101000111 )
b00000000000001001111111010011001 *
b00000000000001000000010011101101 +
b00000000000000110000011100111011 ,
b00000000000000100000011010000010 -
b00000000000000010000001111000010 .
14
#140000
04
b00000000000010110001001011001001 6
b00000000000000000000000000001100 7
#145000
b00000000000001001000001110000111 #
b00000000000010110001001011001001 $
b00000000000010100100111100110010 %
b00000000000010011000000101001101 &
b00000000000010001010100111101000 '
b00000000000001111100100111011001 (
b00000000000001101110001000000000 )
b00000000000001011111001101000111 *
b00000000000001001111111010011001 +
b00000000000001000000010011101101 ,
b00000000000000110000011100111011 -
b00000000000000100000011010000010 .
b00000000000000010000001111000010 /
14
#150000
04
b00000000000010111100101101001111 6
b00000000000000000000000000001101 7
#155000
b00000000000001010110100010010101 #
b00000000000010111100101101001111 $
b00000000000010110001001011001001 %
b00000000000010100100111100110010 &
b00000000000010011000000101001101 '
b00000000000010001010100111101000 (
b00000000000001111100100111011001 )
b00000000000001101110001000000000 *
b00000000000001011111001101000111 +
b00000000000001001111111010011001 ,
b00000000000001000000010011101101 -
b00000000000000110000011100111011 .
b00000000000000100000011010000010 /
b00000000000000010000001111000010 0
14
#160000
04
b00000000000011000111100000001100 6
b00000000000000000000000000001110 7
#165000
b00000000000001100100111110011010 #
b00000000000011000111100000001100 $
b00000000000010111100101101001111 %
b00000000000010110001001011001001 &
b00000000000010100100111100110010 '
b00000000000010011000000101001101 (
b00000000000010001010100111101000 )
b00000000000001111100100111011001 *
b00000000000001101110001000000000 +
b00000000000001011111001101000111 ,
b00000000000001001111111010011001 -
b00000000000001000000010011101101 .
b00000000000000110000011100111011 /
b00000000000000100000011010000010 0
b00000000000000010000001111000010 1
14
#170000
04
b00000000000011010001100001010101 6
b00000000000000000000000000001111 7
#175000
b00000000000001110011010000011110 #
b00000000000011010001100001010101 $
b00000000000011000111100000001100 %
b00000000000010111100101101001111 &
b00000000000010110001001011001001 '
b00000000000010100100111100110010 (
b00000000000010011000000101001101 )
b00000000000010001010100111101000 *
b00000000000001111100100111011001 +
b00000000000001101110001000000000 ,
b00000000000001011111001101000111 -
b00000000000001001111111010011001 .
b00000000000001000000010011101101 /
b00000000000000110000011100111011 0
b00000000000000100000011010000010 1
b00000000000000010000001111000010 2
14
#180000
04
b00000000000011011010101110001010 6
b00000000000000000000000000010000 7
#185000
b00000000000010000001001111111010 #
b00000000000011011010101110001010 $
b00000000000011010001100001010101 %
b00000000000011000111100000001100 &
b00000000000010111100101101001111 '
b00000000000010110001001011001001 (
b00000000000010100100111100110010 )
b00000000000010011000000101001101 *
b00000000000010001010100111101000 +
b00000000000001111100100111011001 ,
b00000000000001101110001000000000 -
b00000000000001011111001101000111 .
b00000000000001001111111010011001 /
b00000000000001000000010011101101 0
b00000000000000110000011100111011 1
b00000000000000100000011010000010 2
b00000000000000010000001111000010 3
14
#190000
04
b00000000000011100011000100011010 6
b00000000000000000000000000010001 7
#195000
b00000000000010001110101111000010 #
b00000000000011100011000100011010 $
b00000000000011011010101110001010 %
b00000000000011010001100001010101 &
b00000000000011000111100000001100 '
b00000000000010111100101101001111 (
b00000000000010110001001011001001 )
b00000000000010100100111100110010 *
b00000000000010011000000101001101 +
b00000000000010001010100111101000 ,
b00000000000001111100100111011001 -
b00000000000001101110001000000000 .
b00000000000001011111001101000111 /
b00000000000001001111111010011001 0
b00000000000001000000010011101101 1
b00000000000000110000011100111011 2
b00000000000000100000011010000010 3
14
#200000
04
b00000000000011101010100001111101 6
b00000000000000000000000000010010 7
#205000
b00000000000010011011101010100000 #
b00000000000011101010100001111101 $
b00000000000011100011000100011010 %
b00000000000011011010101110001010 &
b00000000000011010001100001010101 '
b00000000000011000111100000001100 (
b00000000000010111100101101001111 )
b00000000000010110001001011001001 *
b00000000000010100100111100110010 +
b00000000000010011000000101001101 ,
b00000000000010001010100111101000 -
b00000000000001111100100111011001 .
b00000000000001101110001000000000 /
b00000000000001011111001101000111 0
b00000000000001001111111010011001 1
b00000000000001000000010011101101 2
b00000000000000110000011100111011 3
14
#210000
04
b00000000000011110001000101000010 6
b00000000000000000000000000010011 7
#215000
b00000000000010100111111111000011 #
b00000000000011110001000101000010 $
b00000000000011101010100001111101 %
b00000000000011100011000100011010 &
b00000000000011011010101110001010 '
b00000000000011010001100001010101 (
b00000000000011000111100000001100 )
b00000000000010111100101101001111 *
b00000000000010110001001011001001 +
b00000000000010100100111100110010 ,
b00000000000010011000000101001101 -
b00000000000010001010100111101000 .
b00000000000001111100100111011001 /
b00000000000001101110001000000000 0
b00000000000001011111001101000111 1
b00000000000001001111111010011001 2
b00000000000001000000010011101101 3
14
#220000
04
b00000000000011110110101011111111 6
b00000000000000000000000000010100 7
#225000
b00000000000010110011101001101001 #
b00000000000011110110101011111111 $
b00000000000011110001000101000010 %
b00000000000011101010100001111101 &
b00000000000011100011000100011010 '
b00000000000011011010101110001010 (
b00000000000011010001100001010101 )
b00000000000011000111100000001100 *
b00000000000010111100101101001111 +
b00000000000010110001001011001001 ,
b00000000000010100100111100110010 -
b00000000000010011000000101001101 .
b00000000000010001010100111101000 /
b00000000000001111100100111011001 0
b00000000000001101110001000000000 1
b00000000000001011111001101000111 2
b00000000000001001111111010011001 3
14
#230000
04
b00000000000011111011010101011100 6
b00000000000000000000000000010101 7
#235000
b00000000000010111110100111010110 #
b00000000000011111011010101011100 $
b00000000000011110110101011111111 %
b00000000000011110001000101000010 &
b00000000000011101010100001111101 '
b00000000000011100011000100011010 (
b00000000000011011010101110001010 )
b00000000000011010001100001010101 *
b00000000000011000111100000001100 +
b00000000000010111100101101001111 ,
b00000000000010110001001011001001 -
b00000000000010100100111100110010 .
b00000000000010011000000101001101 /
b00000000000010001010100111101000 0
b00000000000001111100100111011001 1
b00000000000001101110001000000000 2
b00000000000001011111001101000111 3
14
#240000
04
b00000000000011111111000000010000 6
b00000000000000000000000000010110 7
#245000
b00000000000011001000110101100011 #
b00000000000011111111000000010000 $
b00000000000011111011010101011100 %
b00000000000011110110101011111111 &
b00000000000011110001000101000010 '
b00000000000011101010100001111101 (
b00000000000011100011000100011010 )
b00000000000011011010101110001010 *
b00000000000011010001100001010101 +
b00000000000011000111100000001100 ,
b00000000000010111100101101001111 -
b00000000000010110001001011001001 .
b00000000000010100100111100110010 /
b00000000000010011000000101001101 0
b00000000000010001010100111101000 1
b00000000000001111100100111011001 2
b00000000000001101110001000000000 3
14
#250000
04
b00000000000100000001101011100011 6
b00000000000000000000000000010111 7
#255000
b00000000000011010010010001100000 #
b00000000000100000001101011100011 $
b00000000000011111111000000010000 %
b00000000000011111011010101011100 &
b00000000000011110110101011111111 '
b00000000000011110001000101000010 (
b00000000000011101010100001111101 )
b00000000000011100011000100011010 *
b00000000000011011010101110001010 +
b00000000000011010001100001010101 ,
b00000000000011000111100000001100 -
b00000000000010111100101101001111 .
b00000000000010110001001011001001 /
b00000000000010100100111100110010 0
b00000000000010011000000101001101 1
b00000000000010001010100111101000 2
b00000000000001111100100111011001 3
14
#260000
04
b00000000000100000011010110101101 6
b00000000000000000000000000011000 7
#265000
b00000000000011011010111000111110 #
b00000000000100000011010110101101 $
b00000000000100000001101011100011 %
b00000000000011111111000000010000 &
b00000000000011111011010101011100 '
b00000000000011110110101011111111 (
b00000000000011110001000101000010 )
b00000000000011101010100001111101 *
b00000000000011100011000100011010 +
b00000000000011011010101110001010 ,
b00000000000011010001100001010101 -
b00000000000011000111100000001100 .
b00000000000010111100101101001111 /
b00000000000010110001001011001001 0
b00000000000010100100111100110010 1
b00000000000010011000000101001101 2
b00000000000010001010100111101000 3
14
#270000
04
b00000000000100000100000001010110 6
b00000000000000000000000000011001 7
#275000
b00000000000011100010101001111011 #
b00000000000100000100000001010110 $
b00000000000100000011010110101101 %
b00000000000100000001101011100011 &
b00000000000011111111000000010000 '
b00000000000011111011010101011100 (
b00000000000011110110101011111111 )
b00000000000011110001000101000010 *
b00000000000011101010100001111101 +
b00000000000011100011000100011010 ,
b00000000000011011010101110001010 -
b00000000000011010001100001010101 .
b00000000000011000111100000001100 /
b00000000000010111100101101001111 0
b00000000000010110001001011001001 1
b00000000000010100100111100110010 2
b00000000000010011000000101001101 3
14
#280000
04
b00000000000100000011101011010011 6
b00000000000000000000000000011010 7
#285000
b00000000000011101001100010010001 #
b00000000000100000011101011010011 $
b00000000000100000100000001010110 %
b00000000000100000011010110101101 &
b00000000000100000001101011100011 '
b00000000000011111111000000010000 (
b00000000000011111011010101011100 )
b00000000000011110110101011111111 *
b00000000000011110001000101000010 +
b00000000000011101010100001111101 ,
b00000000000011100011000100011010 -
b00000000000011011010101110001010 .
b00000000000011010001100001010101 /
b00000000000011000111100000001100 0
b00000000000010111100101101001111 1
b00000000000010110001001011001001 2
b00000000000010100100111100110010 3
14
#290000
04
b00000000000100000010010100101110 6
b00000000000000000000000000011011 7
#295000
b00000000000011101111100000011001 #
b00000000000100000010010100101110 $
b00000000000100000011101011010011 %
b00000000000100000100000001010110 &
b00000000000100000011010110101101 '
b00000000000100000001101011100011 (
b00000000000011111111000000010000 )
b00000000000011111011010101011100 *
b00000000000011110110101011111111 +
b00000000000011110001000101000010 ,
b00000000000011101010100001111101 -
b00000000000011100011000100011010 .
b00000000000011011010101110001010 /
b00000000000011010001100001010101 0
b00000000000011000111100000001100 1
b00000000000010111100101101001111 2
b00000000000010110001001011001001 3
14
#300000
04
b00000000000011111111111110000000 6
b00000000000000000000000000011100 7
#305000
b00000000000011110100100010110011 #
b00000000000011111111111110000000 $
b00000000000100000010010100101110 %
b00000000000100000011101011010011 &
b00000000000100000100000001010110 '
b00000000000100000011010110101101 (
b00000000000100000001101011100011 )
b00000000000011111111000000010000 *
b00000000000011111011010101011100 +
b00000000000011110110101011111111 ,
b00000000000011110001000101000010 -
b00000000000011101010100001111101 .
b00000000000011100011000100011010 /
b00000000000011011010101110001010 0
b00000000000011010001100001010101 1
b00000000000011000111100000001100 2
b00000000000010111100101101001111 3
14
#310000
04
b00000000000011111100100111110010 6
b00000000000000000000000000011101 7
#315000
b00000000000011111000101000010100 #
b00000000000011111100100111110010 $
b00000000000011111111111110000000 %
b00000000000100000010010100101110 &
b00000000000100000011101011010011 '
b00000000000100000100000001010110 (
b00000000000100000011010110101101 )
b00000000000100000001101011100011 *
b00000000000011111111000000010000 +
b00000000000011111011010101011100 ,
b00000000000011110110101011111111 -
b00000000000011110001000101000010 .
b00000000000011101010100001111101 /
b00000000000011100011000100011010 0
b00000000000011011010101110001010 1
b00000000000011010001100001010101 2
b00000000000011000111100000001100 3
14
#320000
04
b00000000000011111000010010111011 6
b00000000000000000000000000011110 7
#325000
b00000000000011111011101111111000 #
b00000000000011111000010010111011 $
b00000000000011111100100111110010 %
b00000000000011111111111110000000 &
b00000000000100000010010100101110 '
b00000000000100000011101011010011 (
b00000000000100000100000001010110 )
b00000000000100000011010110101101 *
b00000000000100000001101011100011 +
b00000000000011111111000000010000 ,
b00000000000011111011010101011100 -
b00000000000011110110101011111111 .
b00000000000011110001000101000010 /
b00000000000011101010100001111101 0
b00000000000011100011000100011010 1
b00000000000011011010101110001010 2
b00000000000011010001100001010101 3
14
#330000
04
b00000000000011110011000000100011 6
b00000000000000000000000000011111 7
#335000
b00000000000011111101111000101111 #
b00000000000011110011000000100011 $
b00000000000011111000010010111011 %
b00000000000011111100100111110010 &
b00000000000011111111111110000000 '
b00000000000100000010010100101110 (
b00000000000100000011101011010011 )
b00000000000100000100000001010110 *
b00000000000100000011010110101101 +
b00000000000100000001101011100011 ,
b00000000000011111111000000010000 -
b00000000000011111011010101011100 .
b00000000000011110110101011111111 /
b00000000000011110001000101000010 0
b00000000000011101010100001111101 1
b00000000000011100011000100011010 2
b00000000000011011010101110001010 3
14
#340000
04
b00000000000011101100110010000100 6
b00000000000000000000000000100000 7
#345000
b00000000000011111111000010011101 #
b00000000000011101100110010000100 $
b00000000000011110011000000100011 %
b00000000000011111000010010111011 &
b00000000000011111100100111110010 '
b00000000000011111111111110000000 (
b00000000000100000010010100101110 )
b00000000000100000011101011010011 *
b00000000000100000100000001010110 +
b00000000000100000011010110101101 ,
b00000000000100000001101011100011 -
b00000000000011111111000000010000 .
b00000000000011111011010101011100 /
b00000000000011110110101011111111 0
b00000000000011110001000101000010 1
b00000000000011101010100001111101 2
b00000000000011100011000100011010 3
14
#350000
04
b00000000000011100101101001000110 6
b00000000000000000000000000100001 7
#355000
b00000000000011111111001100110010 #
b00000000000011100101101001000110 $
b00000000000011101100110010000100 %
b00000000000011110011000000100011 &
b00000000000011111000010010111011 '
b00000000000011111100100111110010 (
b00000000000011111111111110000000 )
b00000000000100000010010100101110 *
b00000000000100000011101011010011 +
b00000000000100000100000001010110 ,
b00000000000100000011010110101101 -
b00000000000100000001101011100011 .
b00000000000011111111000000010000 /
b00000000000011111011010101011100 0
b00000000000011110110101011111111 1
b00000000000011110001000101000010 2
b00000000000011101010100001111101 3
14
#360000
04
b00000000000011011101100111011011 6
b00000000000000000000000000100010 7
#365000
b00000000000011111110010111100111 #
b00000000000011011101100111011011 $
b00000000000011100101101001000110 %
b00000000000011101100110010000100 &
b00000000000011110011000000100011 '
b00000000000011111000010010111011 (
b00000000000011111100100111110010 )
b00000000000011111111111110000000 *
b00000000000100000010010100101110 +
b00000000000100000011101011010011 ,
b00000000000100000100000001010110 -
b00000000000100000011010110101101 .
b00000000000100000001101011100011 /
b00000000000011111111000000010000 0
b00000000000011111011010101011100 1
b00000000000011110110101011111111 2
b00000000000011110001000101000010 3
14
#370000
04
b00000000000011010100101111001100 6
b00000000000000000000000000100011 7
#375000
b00000000000011111100100011010101 #
b00000000000011010100101111001100 $
b00000000000011011101100111011011 %
b00000000000011100101101001000110 &
b00000000000011101100110010000100 '
b00000000000011110011000000100011 (
b00000000000011111000010010111011 )
b00000000000011111100100111110010 *
b00000000000011111111111110000000 +
b00000000000100000010010100101110 ,
b00000000000100000011101011010011 -
b00000000000100000100000001010110 .
b00000000000100000011010110101101 /
b00000000000100000001101011100011 0
b00000000000011111111000000010000 1
b00000000000011111011010101011100 2
b00000000000011110110101011111111 3
14
#380000
04
b00000000000011001011000010101001 6
b00000000000000000000000000100100 7
#385000
b00000000000011111001110000011000 #
b00000000000011001011000010101001 $
b00000000000011010100101111001100 %
b00000000000011011101100111011011 &
b00000000000011100101101001000110 '
b00000000000011101100110010000100 (
b00000000000011110011000000100011 )
b00000000000011111000010010111011 *
b00000000000011111100100111110010 +
b00000000000011111111111110000000 ,
b00000000000100000010010100101110 -
b00000000000100000011101011010011 .
b00000000000100000100000001010110 /
b00000000000100000011010110101101 0
b00000000000100000001101011100011 1
b00000000000011111111000000010000 2
b00000000000011111011010101011100 3
14
#390000
04
b00000000000011000000100100010001 6
b00000000000000000000000000100101 7
#395000
b00000000000011110101111111011110 #
b00000000000011000000100100010001 $
b00000000000011001011000010101001 %
b00000000000011010100101111001100 &
b00000000000011011101100111011011 '
b00000000000011100101101001000110 (
b00000000000011101100110010000100 )
b00000000000011110011000000100011 *
b00000000000011111000010010111011 +
b00000000000011111100100111110010 ,
b00000000000011111111111110000000 -
b00000000000100000010010100101110 .
b00000000000100000011101011010011 /
b00000000000100000100000001010110 0
b00000000000100000011010110101101 1
b00000000000100000001101011100011 2
b00000000000011111111000000010000 3
14
#400000
04
b00000000000010110101010110110000 6
b00000000000000000000000000100110 7
#405000
b00000000000011110001010001100111 #
b00000000000010110101010110110000 $
b00000000000011000000100100010001 %
b00000000000011001011000010101001 &
b00000000000011010100101111001100 '
b00000000000011011101100111011011 (
b00000000000011100101101001000110 )
b00000000000011101100110010000100 *
b00000000000011110011000000100011 +
b00000000000011111000010010111011 ,
b00000000000011111100100111110010 -
b00000000000011111111111110000000 .
b00000000000100000010010100101110 /
b00000000000100000011101011010011 0
b00000000000100000100000001010110 1
b00000000000100000011010110101101 2
b00000000000100000001101011100011 3
14
#410000
04
b00000000000010101001011100111111 6
b00000000000000000000000000100111 7
#415000
b00000000000011101011101000000101 #
b00000000000010101001011100111111 $
b00000000000010110101010110110000 %
b00000000000011000000100100010001 &
b00000000000011001011000010101001 '
b00000000000011010100101111001100 (
b00000000000011011101100111011011 )
b00000000000011100101101001000110 *
b00000000000011101100110010000100 +
b00000000000011110011000000100011 ,
b00000000000011111000010010111011 -
b00000000000011111100100111110010 .
b00000000000011111111111110000000 /
b00000000000100000010010100101110 0
b00000000000100000011101011010011 1
b00000000000100000100000001010110 2
b00000000000100000011010110101101 3
14
#420000
04
b00000000000010011100111001111111 6
b00000000000000000000000000101000 7
#425000
b00000000000011100101000100010101 #
b00000000000010011100111001111111 $
b00000000000010101001011100111111 %
b00000000000010110101010110110000 &
b00000000000011000000100100010001 '
b00000000000011001011000010101001 (
b00000000000011010100101111001100 )
b00000000000011011101100111011011 *
b00000000000011100101101001000110 +
b00000000000011101100110010000100 ,
b00000000000011110011000000100011 -
b00000000000011111000010010111011 .
b00000000000011111100100111110010 /
b00000000000011111111111110000000 0
b00000000000100000010010100101110 1
b00000000000100000011101011010011 2
b00000000000100000100000001010110 3
14
#430000
04
b00000000000010001111110001000000 6
b00000000000000000000000000101001 7
#435000
b00000000000011011101101000000000 #
b00000000000010001111110001000000 $
b00000000000010011100111001111111 %
b00000000000010101001011100111111 &
b00000000000010110101010110110000 '
b00000000000011000000100100010001 (
b00000000000011001011000010101001 )
b00000000000011010100101111001100 *
b00000000000011011101100111011011 +
b00000000000011100101101001000110 ,
b00000000000011101100110010000100 -
b00000000000011110011000000100011 .
b00000000000011111000010010111011 /
b00000000000011111100100111110010 0
b00000000000011111111111110000000 1
b00000000000100000010010100101110 2
b00000000000100000011101011010011 3
14
#440000
04
b00000000000010000010000101010111 6
b00000000000000000000000000101010 7
#445000
b00000000000011010101010101000110 #
b00000000000010000010000101010111 $
b00000000000010001111110001000000 %
b00000000000010011100111001111111 &
b00000000000010101001011100111111 '
b00000000000010110101010110110000 (
b00000000000011000000100100010001 )
b00000000000011001011000010101001 *
b00000000000011010100101111001100 +
b00000000000011011101100111011011 ,
b00000000000011100101101001000110 -
b00000000000011101100110010000100 .
b00000000000011110011000000100011 /
b00000000000011111000010010111011 0
b00000000000011111100100111110010 1
b00000000000011111111111110000000 2
b00000000000100000010010100101110 3
14
#450000
04
b00000000000001110011111010100011 6
b00000000000000000000000000101011 7
#455000
b00000000000011001100001101101001 #
b00000000000001110011111010100011 $
b00000000000010000010000101010111 %
b00000000000010001111110001000000 &
b00000000000010011100111001111111 '
b00000000000010101001011100111111 (
b00000000000010110101010110110000 )
b00000000000011000000100100010001 *
b00000000000011001011000010101001 +
b00000000000011010100101111001100 ,
b00000000000011011101100111011011 -
b00000000000011100101101001000110 .
b00000000000011101100110010000100 /
b00000000000011110011000000100011 0
b00000000000011111000010010111011 1
b00000000000011111100100111110010 2
b00000000000011111111111110000000 3
14
#460000
04
b00000000000001100101010100001111 6
b00000000000000000000000000101100 7
#465000
b00000000000011000010010100000111 #
b00000000000001100101010100001111 $
b00000000000001110011111010100011 %
b00000000000010000010000101010111 &
b00000000000010001111110001000000 '
b00000000000010011100111001111111 (
b00000000000010101001011100111111 )
b00000000000010110101010110110000 *
b00000000000011000000100100010001 +
b00000000000011001011000010101001 ,
b00000000000011010100101111001100 -
b00000000000011011101100111011011 .
b00000000000011100101101001000110 /
b00000000000011101100110010000100 0
b00000000000011110011000000100011 1
b00000000000011111000010010111011 2
b00000000000011111100100111110010 3
14
#470000
04
b00000000000001010110010110000110 6
b00000000000000000000000000101101 7
